{
  "updated": "2026-07-20T10:13:31Z",
  "prices": {
    "BTCUSDT": {
      "price": 64203.6992,
      "change": -487.1055,
      "change_pct": -0.75
    },
    "ETHUSDT": {
      "price": 1863.9399,
      "change": -7.5686,
      "change_pct": -0.4
    },
    "ORBS": {
      "price": 0.0059,
      "change": -0.0,
      "change_pct": -0.0
    },
    "GOLD": {
      "price": 4023.5,
      "change": 0.0,
      "change_pct": 0.0
    },
    "XAGUSD": {
      "price": 57.155,
      "change": 0.0,
      "change_pct": 0.0
    },
    "IAG": {
      "price": 14.14,
      "change": -0.06,
      "change_pct": -0.42
    },
    "IMG": {
      "price": 19.78,
      "change": -0.16,
      "change_pct": -0.8
    },
    "UKOIL": {
      "price": 88.13,
      "change": 0.0,
      "change_pct": 0.0
    },
    "WLDUSDT": {
      "price": 0.3615,
      "change": 0.0008,
      "change_pct": 0.22
    },
    "SAP": {
      "price": 159.04,
      "change": -2.6,
      "change_pct": -1.61
    },
    "NEM": {
      "price": 89.7,
      "change": -1.13,
      "change_pct": -1.24
    },
    "ABX": {
      "price": 48.92,
      "change": -0.02,
      "change_pct": -0.04
    },
    "GDX": {
      "price": 71.32,
      "change": -0.08,
      "change_pct": -0.11
    },
    "CCJ": {
      "price": 85.62,
      "change": -1.74,
      "change_pct": -1.99
    },
    "UEC": {
      "price": 9.28,
      "change": -0.05,
      "change_pct": -0.54
    }
  }
}