{
  "updated": "2026-07-01T16:08:05Z",
  "prices": {
    "BTCUSDT": {
      "price": 60155.7812,
      "change": 1596.9219,
      "change_pct": 2.73
    },
    "ETHUSDT": {
      "price": 1618.72,
      "change": 49.1361,
      "change_pct": 3.13
    },
    "ORBS": {
      "price": 0.0057,
      "change": 0.0001,
      "change_pct": 1.8
    },
    "GOLD": {
      "price": 4094.6001,
      "change": 71.7002,
      "change_pct": 1.78
    },
    "XAGUSD": {
      "price": 60.68,
      "change": 1.203,
      "change_pct": 2.02
    },
    "IAG": {
      "price": 16.255,
      "change": 0.415,
      "change_pct": 2.62
    },
    "IMG": {
      "price": 22.51,
      "change": -0.13,
      "change_pct": -0.57
    },
    "UKOIL": {
      "price": 71.18,
      "change": -1.74,
      "change_pct": -2.39
    },
    "WLDUSDT": {
      "price": 0.3956,
      "change": -0.0109,
      "change_pct": -2.68
    },
    "SAP": {
      "price": 160.52,
      "change": 6.41,
      "change_pct": 4.16
    },
    "NEM": {
      "price": 94.7,
      "change": 1.3,
      "change_pct": 1.39
    },
    "ABX": {
      "price": 52.15,
      "change": -0.32,
      "change_pct": -0.61
    },
    "GDX": {
      "price": 76.965,
      "change": 1.515,
      "change_pct": 2.01
    },
    "CCJ": {
      "price": 101.55,
      "change": -0.31,
      "change_pct": -0.3
    },
    "UEC": {
      "price": 10.76,
      "change": 0.1,
      "change_pct": 0.94
    }
  }
}